cozyconsole/__init__.py
cozyconsole/activity.py
cozyconsole/consolex.py
cozyconsole/markdownpatcher.py
cozyconsole/demo/__init__.py
cozyconsole/demo/__main__.py
cozyconsole/demo/activity.py
cozyconsole-0.4.1.dist-info/entry_points.txt
cozyconsole-0.4.1.dist-info/LICENSE
cozyconsole-0.4.1.dist-info/WHEEL
cozyconsole-0.4.1.dist-info/METADATA
cozyconsole-0.4.1.dist-info/RECORD
