Metadata-Version: 2.1
Name: cozyconsole
Version: 0.4.1
Summary: Making development of console-based apps a little more convenient
Keywords: cli,console,rich
Author-email: Ralf Luetkemeier <foss@rlue.de>
Requires-Python: >=3.8,<4
Classifier: Development Status :: 4 - Beta
Classifier: Environment :: Console
Classifier: Intended Audience :: Developers
Classifier: License :: OSI Approved :: MIT License
Classifier: Operating System :: MacOS
Classifier: Operating System :: Microsoft :: Windows
Classifier: Operating System :: POSIX :: Linux
Classifier: Programming Language :: Python :: 3
Classifier: Programming Language :: Python :: 3.8
Classifier: Programming Language :: Python :: 3.9
Classifier: Programming Language :: Python :: 3.10
Classifier: Programming Language :: Python :: 3.11
Classifier: Programming Language :: Python :: 3.12
Classifier: Programming Language :: Python :: 3 :: Only
Classifier: Topic :: Software Development
Requires-Dist: rich >=12.0.0, <14.0.0
Requires-Dist: pytest >=7.2.0 ; extra == "test"
Requires-Dist: semver>= 3.0.0 ; extra == "test"
Provides-Extra: test
